{
  "openapi": "3.0.1",
  "info": {
    "title": "OpenApi specification - Oussama Soussi",
    "description": "OpenApi documentation for pi service",
    "contact": {
      "name": "Oussama",
      "email": "oussama.soussi.it@gmail.com"
    },
    "version": "1.0"
  },
  "servers": [
    {
      "url": "http://localhost:3434/operations/",
      "description": "Partie Prenante API"
    }
  ],
  "security": [
    {
      "bearerAuth": []
    }
  ],
  "paths": {
    "/api/operations/pi/creerPi": {
      "post": {
        "tags": [
          "partie-interessee-controller"
        ],
        "operationId": "createPi",
        "requestBody": {
          "content": {
            "application/json": {
              "schema": {
                "$ref": "#/components/schemas/PartieInteresseValue"
              }
            }
          },
          "required": true
        },
        "responses": {
          "200": {
            "description": "OK",
            "content": {
              "*/*": {
                "schema": {
                  "$ref": "#/components/schemas/PartieInteresse"
                }
              }
            }
          }
        }
      }
    },
    "/api/operations/pi/find/by/{id}": {
      "get": {
        "tags": [
          "partie-interessee-controller"
        ],
        "operationId": "findPiById",
        "parameters": [
          {
            "name": "id",
            "in": "path",
            "required": true,
            "schema": {
              "type": "integer",
              "format": "int64"
            }
          }
        ],
        "responses": {
          "200": {
            "description": "OK",
            "content": {
              "*/*": {
                "schema": {
                  "$ref": "#/components/schemas/PartieInteresseValue"
                }
              }
            }
          }
        }
      }
    },
    "/api/operations/pi/find/all": {
      "get": {
        "tags": [
          "partie-interessee-controller"
        ],
        "operationId": "findAll",
        "responses": {
          "200": {
            "description": "OK",
            "content": {
              "application/json": {
                "schema": {
                  "type": "array",
                  "items": {
                    "$ref": "#/components/schemas/PartieInteresseValue"
                  }
                }
              }
            }
          }
        }
      }
    },
    "/api/operations/pi/AbreviationClient/{id}": {
      "get": {
        "tags": [
          "partie-interessee-controller"
        ],
        "operationId": "getAbbreviationClient",
        "parameters": [
          {
            "name": "id",
            "in": "path",
            "required": true,
            "schema": {
              "type": "integer",
              "format": "int64"
            }
          }
        ],
        "responses": {
          "200": {
            "description": "OK",
            "content": {
              "*/*": {
                "schema": {
                  "$ref": "#/components/schemas/PartieInteresseValue"
                }
              }
            }
          }
        }
      }
    },
    "/api/operations/pi/delete/{id}": {
      "delete": {
        "tags": [
          "partie-interessee-controller"
        ],
        "operationId": "deletePi",
        "parameters": [
          {
            "name": "id",
            "in": "path",
            "required": true,
            "schema": {
              "type": "integer",
              "format": "int64"
            }
          }
        ],
        "responses": {
          "200": {
            "description": "OK"
          }
        }
      }
    }
  },
  "components": {
    "schemas": {
      "DocumentPiValue": {
        "type": "object",
        "properties": {
          "id": {
            "type": "integer",
            "format": "int64"
          },
          "partieInteresseId": {
            "type": "integer",
            "format": "int64"
          },
          "path": {
            "type": "string"
          },
          "uidDocument": {
            "type": "string"
          }
        }
      },
      "PartieInteresseValue": {
        "type": "object",
        "properties": {
          "id": {
            "type": "integer",
            "format": "int64"
          },
          "siteId": {
            "type": "integer",
            "format": "int64"
          },
          "reference": {
            "type": "string"
          },
          "matrFiscal": {
            "type": "string"
          },
          "abreviation": {
            "type": "string"
          },
          "adresseLiv": {
            "type": "string"
          },
          "modalitePaiement": {
            "type": "string"
          },
          "documents": {
            "type": "array",
            "items": {
              "$ref": "#/components/schemas/DocumentPiValue"
            }
          },
          "representants": {
            "type": "array",
            "items": {
              "$ref": "#/components/schemas/RepresentantValue"
            }
          }
        }
      },
      "RepresentantValue": {
        "type": "object",
        "properties": {
          "id": {
            "type": "integer",
            "format": "int64"
          },
          "nom": {
            "type": "string"
          },
          "fonction": {
            "type": "string"
          },
          "email": {
            "type": "string"
          },
          "telephone": {
            "type": "string"
          },
          "fax": {
            "type": "string"
          },
          "partieInteresseId": {
            "type": "integer",
            "format": "int64"
          }
        }
      },
      "Document": {
        "type": "object",
        "properties": {
          "creationDate": {
            "type": "string",
            "format": "date-time"
          },
          "modificationDate": {
            "type": "string",
            "format": "date-time"
          },
          "deletionDate": {
            "type": "string",
            "format": "date-time"
          },
          "creatorIdentifier": {
            "type": "string"
          },
          "latestUpdaterId": {
            "type": "string"
          },
          "version": {
            "type": "integer",
            "format": "int64"
          },
          "archived": {
            "type": "boolean"
          },
          "partieInteresse": {
            "$ref": "#/components/schemas/PartieInteresse"
          },
          "id": {
            "type": "integer",
            "format": "int64"
          },
          "path": {
            "type": "string"
          },
          "uidDocument": {
            "type": "string"
          }
        }
      },
      "PartieInteresse": {
        "type": "object",
        "properties": {
          "creationDate": {
            "type": "string",
            "format": "date-time"
          },
          "modificationDate": {
            "type": "string",
            "format": "date-time"
          },
          "deletionDate": {
            "type": "string",
            "format": "date-time"
          },
          "creatorIdentifier": {
            "type": "string"
          },
          "latestUpdaterId": {
            "type": "string"
          },
          "version": {
            "type": "integer",
            "format": "int64"
          },
          "archived": {
            "type": "boolean"
          },
          "documents": {
            "type": "array",
            "items": {
              "$ref": "#/components/schemas/Document"
            }
          },
          "representants": {
            "type": "array",
            "items": {
              "$ref": "#/components/schemas/Representant"
            }
          },
          "id": {
            "type": "integer",
            "format": "int64"
          },
          "siteId": {
            "type": "integer",
            "format": "int64"
          },
          "reference": {
            "type": "string"
          },
          "matrFiscal": {
            "type": "string"
          },
          "abreviation": {
            "type": "string"
          },
          "adresseLiv": {
            "type": "string"
          },
          "modalitePaiement": {
            "type": "string"
          }
        }
      },
      "Representant": {
        "type": "object",
        "properties": {
          "creationDate": {
            "type": "string",
            "format": "date-time"
          },
          "modificationDate": {
            "type": "string",
            "format": "date-time"
          },
          "deletionDate": {
            "type": "string",
            "format": "date-time"
          },
          "creatorIdentifier": {
            "type": "string"
          },
          "latestUpdaterId": {
            "type": "string"
          },
          "version": {
            "type": "integer",
            "format": "int64"
          },
          "archived": {
            "type": "boolean"
          },
          "partieInteresse": {
            "$ref": "#/components/schemas/PartieInteresse"
          },
          "id": {
            "type": "integer",
            "format": "int64"
          },
          "nom": {
            "type": "string"
          },
          "fonction": {
            "type": "string"
          },
          "email": {
            "type": "string"
          },
          "telephone": {
            "type": "string"
          },
          "fax": {
            "type": "string"
          }
        }
      }
    },
    "securitySchemes": {
      "bearerAuth": {
        "type": "oauth2",
        "description": "JWT auth description",
        "in": "header",
        "scheme": "bearer",
        "bearerFormat": "JWT",
        "flows": {
          "clientCredentials": {
            "authorizationUrl": "http://localhost:8080/realms/gpao-realm/protocol/openid-connect/auth",
            "scopes": {

            }
          }
        }
      }
    }
  }
}